odoo/addons/survey_question_type_five_star/README.rst
odoo/addons/survey_question_type_five_star/__init__.py
odoo/addons/survey_question_type_five_star/__manifest__.py
odoo/addons/survey_question_type_five_star/i18n/survey_question_type_five_star.pot
odoo/addons/survey_question_type_five_star/models/__init__.py
odoo/addons/survey_question_type_five_star/models/survey_question.py
odoo/addons/survey_question_type_five_star/models/survey_user_input_line.py
odoo/addons/survey_question_type_five_star/readme/CONTRIBUTORS.rst
odoo/addons/survey_question_type_five_star/readme/DESCRIPTION.rst
odoo/addons/survey_question_type_five_star/static/description/icon.png
odoo/addons/survey_question_type_five_star/static/description/index.html
odoo/addons/survey_question_type_five_star/static/src/js/survey.js
odoo/addons/survey_question_type_five_star/static/src/scss/parameters.scss
odoo/addons/survey_question_type_five_star/static/src/scss/survey.scss
odoo/addons/survey_question_type_five_star/templates/survey_template.xml
odoo/addons/survey_question_type_five_star/tests/__init__.py
odoo/addons/survey_question_type_five_star/tests/test_survey.py
odoo/addons/survey_question_type_five_star/views/survey_question.xml
odoo14_addon_survey_question_type_five_star-14.0.1.0.1.dist-info/METADATA
odoo14_addon_survey_question_type_five_star-14.0.1.0.1.dist-info/WHEEL
odoo14_addon_survey_question_type_five_star-14.0.1.0.1.dist-info/top_level.txt
odoo14_addon_survey_question_type_five_star-14.0.1.0.1.dist-info/RECORD
